chaosplt_scheduler/__init__.py
chaosplt_scheduler/__main__.py
chaosplt_scheduler/cli.py
chaosplt_scheduler/log.py
chaosplt_scheduler/logging.json
chaosplt_scheduler/rpc.py
chaosplt_scheduler/rq_worker.py
chaosplt_scheduler/runner.py
chaosplt_scheduler/scheduler.py
chaosplt_scheduler/server.py
chaosplt_scheduler/service.py
chaosplt_scheduler/settings.py
chaosplt_scheduler/worker.py
chaosplatform_scheduler-0.2.0.dist-info/LICENSE
chaosplatform_scheduler-0.2.0.dist-info/METADATA
chaosplatform_scheduler-0.2.0.dist-info/WHEEL
chaosplatform_scheduler-0.2.0.dist-info/entry_points.txt
chaosplatform_scheduler-0.2.0.dist-info/top_level.txt
chaosplatform_scheduler-0.2.0.dist-info/RECORD
