Metadata-Version: 2.1
Name: chaosplatform-scheduler
Version: 0.2.0
Summary: The scheduler service of the Chaos Platform
Home-page: https://github.com/chaostoolkit/chaosplatform-scheduler
Author: ChaosIQ
Author-email: contact@chaosiq.io
License: Apache Software License 2.0
Project-URL: CI: Travis, https://travis-ci.org/chaostoolkit/chaosplatform-scheduler
Project-URL: Docs: RTD, https://docs.chaosplatform.org
Project-URL: GitHub: issues, https://chaostoolkit/chaostoolkit/chaosplatform-scheduler/issues
Project-URL: GitHub: repo, https://chaostoolkit/chaostoolkit/chaosplatform-scheduler
Platform: UNKNOWN
Classifier: Development Status :: 4 - Beta
Classifier: Intended Audience :: Developers
Classifier: License :: OSI Approved :: Apache Software License
Classifier: Operating System :: Unix
Classifier: Operating System :: POSIX
Classifier: Programming Language :: Python
Classifier: Programming Language :: Python :: 3
Classifier: Programming Language :: Python :: 3.6
Classifier: Programming Language :: Python :: 3.7
Classifier: Programming Language :: Python :: 3 :: Only
Classifier: Programming Language :: Python :: Implementation :: CPython
Requires-Python: >=3.6.*
Requires-Dist: Click (>=7.0)
Requires-Dist: cryptography (>=2.3.1)
Requires-Dist: itsdangerous (>=0.24)
Requires-Dist: cherrypy (>=18.0.1)
Requires-Dist: dateparser (>=0.7.0)
Requires-Dist: simplejson (>=3.15.0)
Requires-Dist: grpcio (>=1.17.1)
Requires-Dist: chaosplatform-grpc (>=0.1.0)
Requires-Dist: croniter (>=0.3.26)
Requires-Dist: redis (>=3.0.1)
Requires-Dist: rq (>=0.13.0)
Requires-Dist: rq-scheduler (>=0.9)
Requires-Dist: psutil (>=5.4.8)
Requires-Dist: chaostoolkit-lib (>=1.0.0rc1)
Requires-Dist: toml (>=0.10.0)
